randomv2/__init__.py
randomv2/core.py
randomv2-0.1.dist-info/LICENSE
randomv2-0.1.dist-info/METADATA
randomv2-0.1.dist-info/WHEEL
randomv2-0.1.dist-info/top_level.txt
randomv2-0.1.dist-info/RECORD
