Metadata-Version: 2.2
Name: randomv2
Version: 0.1
Summary: An extended random module with extra probability functions
Author: Adasrh V H
License: MIT
Classifier: License :: OSI Approved :: MIT License
Classifier: Programming Language :: Python :: 3
License-File: LICENSE
Dynamic: author
Dynamic: classifier
Dynamic: license
Dynamic: summary
